{
    "type": "FeatureCollection",
    "features": [
        {
            "type": "Feature",
            "properties": {
                "id": "LEMD-ES",
                "prefix": [
                    "LEMD_ES"
                ],
                "name": "Madrid Approach",
                "label_lat": 40.366,
                "label_lon": -2.152
            },
            "geometry": {
                "type": "MultiPolygon",
                "coordinates": [
                    [
                        [
                            [
                                -2.1583333330744856,
                                40.088888888859714
                            ],
                            [
                                -2.1583333330744856,
                                40.717499999724573
                            ],
                            [
                                -2.5591861108047271,
                                40.617258332717881
                            ],
                            [
                                -2.6319888890266525,
                                40.598875000048125
                            ],
                            [
                                -2.8641916669570939,
                                40.539872222206661
                            ],
                            [
                                -2.9880666667592948,
                                40.508166667178379
                            ],
                            [
                                -3.1000000003669892,
                                40.593055555881541
                            ],
                            [
                                -3.1233333329351751,
                                40.609722221894458
                            ],
                            [
                                -3.1813888886509281,
                                40.543333332808174
                            ],
                            [
                                -3.2640118079120226,
                                40.449238547818105
                            ],
                            [
                                -3.5111111110437907,
                                40.427777778027924
                            ],
                            [
                                -3.4419916671335744,
                                40.245452778102113
                            ],
                            [
                                -3.3536111110432514,
                                40.010833332750622
                            ],
                            [
                                -3.2991666668869661,
                                39.865555556343182
                            ],
                            [
                                -3.1944444442382132,
                                39.583333333091751
                            ],
                            [
                                -2.9180555559963772,
                                39.590277777927668
                            ],
                            [
                                -2.1583333330744856,
                                40.088888888859714
                            ]
                        ]
                    ]
                ]
            }
        }
    ]
}