{
  "type": "Feature",
  "properties": {
    "id": "SBXT",
    "prefix": [
      "SBXT"
    ],
    "name": "Natal Control"
  },
  "geometry": {
    "type": "MultiPolygon",
    "coordinates": [
      [
        [
          [
            -34.7747,
            -6.8447
          ],
          [
            -35.43,
            -6.9403
          ],
          [
            -35.9694,
            -6.4458
          ],
          [
            -36.3275,
            -5.9425
          ],
          [
            -36.4206,
            -5.5719
          ],
          [
            -36.0306,
            -5.1206
          ],
          [
            -35.0864,
            -5.4228
          ],
          [
            -34.7344,
            -5.2567
          ],
          [
            -34.4639,
            -5.6686
          ],
          [
            -34.7397,
            -5.9222
          ],
          [
            -34.7747,
            -6.8447
          ]
        ]
      ]
    ]
  }
}