{
  "type": "Feature",
  "properties": {
    "id": "ZBAA_F",
    "prefix": [
      "ZBAA_F"
    ],
    "name": "Capital Approach"
  },
  "geometry": {
    "type": "MultiPolygon",
    "coordinates": [
      [
        [
          [
            115.93166666667,
            40.382777777778
          ],
          [
            115.98694444444,
            40.019444444444
          ],
          [
            116.32722222222,
            40.05
          ],
          [
            116.36555555556,
            39.801388888889
          ],
          [
            116.41111111111,
            39.504166666667
          ],
          [
            116.57222222222,
            39.5175
          ],
          [
            116.63666666667,
            39.522777777778
          ],
          [
            116.69138888889,
            39.543333333333
          ],
          [
            116.84055555556,
            39.599444444444
          ],
          [
            116.97055555556,
            39.648055555556
          ],
          [
            116.90777777778,
            40.098055555556
          ],
          [
            116.85722222222,
            40.458333333333
          ],
          [
            116.54777777778,
            40.433888888889
          ],
          [
            116.41916666667,
            40.423888888889
          ]
        ]
      ]
    ]
  }
}