{
  "type": "Feature",
  "properties": {
    "id": "URMG",
    "prefix": [
      "URMG_R"
    ],
    "name": "Grozny Tower"
  },
  "geometry": {
    "type": "MultiPolygon",
    "coordinates": [
      [
        [
          [
            46.26167,
            43.56333
          ],
          [
            46.15833,
            43.685
          ],
          [
            45.42528,
            43.73639
          ],
          [
            45.3,
            43.59972
          ],
          [
            45.33333,
            43.35
          ],
          [
            45.95,
            43.36667
          ],
          [
            46.08333,
            43.48333
          ],
          [
            46.26167,
            43.56333
          ]
        ]
      ]
    ]
  }
}