{
  "type": "Feature",
  "properties": {
    "id": "OETB",
    "prefix": [
      "OETB"
    ],
    "name": "Tabuk Approach"
  },
  "geometry": {
    "type": "MultiPolygon",
    "coordinates": [
      [
        [
          [
            36.596952,
            29.03081
          ],
          [
            36.583659,
            29.030503
          ],
          [
            36.570374,
            29.029993
          ],
          [
            36.557101,
            29.029279
          ],
          [
            36.543845,
            29.028361
          ],
          [
            36.530609,
            29.027239
          ],
          [
            36.517398,
            29.025915
          ],
          [
            36.504216,
            29.024387
          ],
          [
            36.491067,
            29.022658
          ],
          [
            36.477955,
            29.020727
          ],
          [
            36.464883,
            29.018594
          ],
          [
            36.451857,
            29.016262
          ],
          [
            36.438881,
            29.01373
          ],
          [
            36.425957,
            29.010998
          ],
          [
            36.41309,
            29.008069
          ],
          [
            36.400285,
            29.004943
          ],
          [
            36.387545,
            29.00162
          ],
          [
            36.374874,
            28.998103
          ],
          [
            36.362276,
            28.994391
          ],
          [
            36.349755,
            28.990486
          ],
          [
            36.337314,
            28.98639
          ],
          [
            36.324958,
            28.982103
          ],
          [
            36.312691,
            28.977628
          ],
          [
            36.300516,
            28.972964
          ],
          [
            36.288437,
            28.968114
          ],
          [
            36.276458,
            28.96308
          ],
          [
            36.264582,
            28.957862
          ],
          [
            36.252813,
            28.952463
          ],
          [
            36.241155,
            28.946884
          ],
          [
            36.229611,
            28.941127
          ],
          [
            36.218185,
            28.935193
          ],
          [
            36.206881,
            28.929085
          ],
          [
            36.195701,
            28.922804
          ],
          [
            36.18465,
            28.916352
          ],
          [
            36.17373,
            28.909732
          ],
          [
            36.162946,
            28.902945
          ],
          [
            36.152299,
            28.895994
          ],
          [
            36.141795,
            28.88888
          ],
          [
            36.131435,
            28.881606
          ],
          [
            36.121223,
            28.874174
          ],
          [
            36.111163,
            28.866586
          ],
          [
            36.101257,
            28.858845
          ],
          [
            36.091507,
            28.850953
          ],
          [
            36.081919,
            28.842912
          ],
          [
            36.072493,
            28.834726
          ],
          [
            36.063233,
            28.826396
          ],
          [
            36.054142,
            28.817925
          ],
          [
            36.045223,
            28.809316
          ],
          [
            36.036478,
            28.800571
          ],
          [
            36.02791,
            28.791693
          ],
          [
            36.019521,
            28.782685
          ],
          [
            36.011315,
            28.77355
          ],
          [
            36.003293,
            28.764289
          ],
          [
            35.995458,
            28.754908
          ],
          [
            35.987812,
            28.745407
          ],
          [
            35.980358,
            28.73579
          ],
          [
            35.973098,
            28.726061
          ],
          [
            35.966034,
            28.716221
          ],
          [
            35.959169,
            28.706275
          ],
          [
            35.952503,
            28.696224
          ],
          [
            35.94604,
            28.686073
          ],
          [
            35.939781,
            28.675824
          ],
          [
            35.933728,
            28.66548
          ],
          [
            35.927883,
            28.655046
          ],
          [
            35.922247,
            28.644523
          ],
          [
            35.916822,
            28.633915
          ],
          [
            35.911611,
            28.623225
          ],
          [
            35.906613,
            28.612457
          ],
          [
            35.901832,
            28.601614
          ],
          [
            35.897268,
            28.590699
          ],
          [
            35.892922,
            28.579716
          ],
          [
            35.888796,
            28.568668
          ],
          [
            35.884891,
            28.557558
          ],
          [
            35.881209,
            28.546389
          ],
          [
            35.877749,
            28.535166
          ],
          [
            35.874514,
            28.523892
          ],
          [
            35.871504,
            28.512569
          ],
          [
            35.868719,
            28.501202
          ],
          [
            35.866162,
            28.489795
          ],
          [
            35.863832,
            28.478349
          ],
          [
            35.861729,
            28.46687
          ],
          [
            35.859856,
            28.455359
          ],
          [
            35.858212,
            28.443822
          ],
          [
            35.856797,
            28.432262
          ],
          [
            35.855612,
            28.420681
          ],
          [
            35.854658,
            28.409084
          ],
          [
            35.853933,
            28.397475
          ],
          [
            35.85344,
            28.385856
          ],
          [
            35.853177,
            28.374231
          ],
          [
            35.853144,
            28.362603
          ],
          [
            35.853343,
            28.350977
          ],
          [
            35.853771,
            28.339356
          ],
          [
            35.85443,
            28.327743
          ],
          [
            35.855319,
            28.316142
          ],
          [
            35.856437,
            28.304557
          ],
          [
            35.857785,
            28.29299
          ],
          [
            35.859361,
            28.281446
          ],
          [
            35.861166,
            28.269928
          ],
          [
            35.863198,
            28.258439
          ],
          [
            35.865457,
            28.246984
          ],
          [
            35.867942,
            28.235564
          ],
          [
            35.870652,
            28.224185
          ],
          [
            35.873587,
            28.212849
          ],
          [
            35.876745,
            28.201559
          ],
          [
            35.880125,
            28.19032
          ],
          [
            35.883727,
            28.179135
          ],
          [
            35.887549,
            28.168006
          ],
          [
            35.89159,
            28.156938
          ],
          [
            35.895848,
            28.145934
          ],
          [
            35.900323,
            28.134997
          ],
          [
            35.905012,
            28.12413
          ],
          [
            35.909915,
            28.113336
          ],
          [
            35.91503,
            28.10262
          ],
          [
            35.920354,
            28.091984
          ],
          [
            35.925888,
            28.081431
          ],
          [
            35.931628,
            28.070965
          ],
          [
            35.937573,
            28.060588
          ],
          [
            35.943721,
            28.050304
          ],
          [
            35.950071,
            28.040117
          ],
          [
            35.956619,
            28.030028
          ],
          [
            35.963365,
            28.020041
          ],
          [
            35.970306,
            28.01016
          ],
          [
            35.97744,
            28.000386
          ],
          [
            35.984765,
            27.990724
          ],
          [
            35.992279,
            27.981175
          ],
          [
            35.999978,
            27.971744
          ],
          [
            36.007862,
            27.962432
          ],
          [
            36.015926,
            27.953242
          ],
          [
            36.02417,
            27.944178
          ],
          [
            36.03259,
            27.935242
          ],
          [
            36.041184,
            27.926436
          ],
          [
            36.04995,
            27.917763
          ],
          [
            36.058884,
            27.909227
          ],
          [
            36.067983,
            27.900829
          ],
          [
            36.077246,
            27.892572
          ],
          [
            36.086669,
            27.884458
          ],
          [
            36.096249,
            27.876491
          ],
          [
            36.105984,
            27.868671
          ],
          [
            36.11587,
            27.861003
          ],
          [
            36.125904,
            27.853487
          ],
          [
            36.136085,
            27.846127
          ],
          [
            36.146407,
            27.838924
          ],
          [
            36.156869,
            27.83188
          ],
          [
            36.167466,
            27.824999
          ],
          [
            36.178197,
            27.818281
          ],
          [
            36.189057,
            27.811728
          ],
          [
            36.200044,
            27.805344
          ],
          [
            36.211153,
            27.799129
          ],
          [
            36.222382,
            27.793086
          ],
          [
            36.233728,
            27.787216
          ],
          [
            36.245186,
            27.781522
          ],
          [
            36.256754,
            27.776004
          ],
          [
            36.268427,
            27.770664
          ],
          [
            36.280203,
            27.765505
          ],
          [
            36.292078,
            27.760527
          ],
          [
            36.304049,
            27.755733
          ],
          [
            36.31611,
            27.751123
          ],
          [
            36.32826,
            27.746699
          ],
          [
            36.340495,
            27.742462
          ],
          [
            36.35281,
            27.738413
          ],
          [
            36.365202,
            27.734555
          ],
          [
            36.377668,
            27.730887
          ],
          [
            36.390203,
            27.727411
          ],
          [
            36.402804,
            27.724128
          ],
          [
            36.415467,
            27.72104
          ],
          [
            36.428189,
            27.718146
          ],
          [
            36.440964,
            27.715448
          ],
          [
            36.453791,
            27.712946
          ],
          [
            36.466664,
            27.710642
          ],
          [
            36.47958,
            27.708536
          ],
          [
            36.492536,
            27.706629
          ],
          [
            36.505526,
            27.704921
          ],
          [
            36.518548,
            27.703412
          ],
          [
            36.531597,
            27.702104
          ],
          [
            36.54467,
            27.700996
          ],
          [
            36.557763,
            27.70009
          ],
          [
            36.570871,
            27.699384
          ],
          [
            36.583991,
            27.69888
          ],
          [
            36.597118,
            27.698578
          ],
          [
            36.61025,
            27.698477
          ],
          [
            36.623382,
            27.698578
          ],
          [
            36.636509,
            27.69888
          ],
          [
            36.649629,
            27.699384
          ],
          [
            36.662737,
            27.70009
          ],
          [
            36.67583,
            27.700996
          ],
          [
            36.688903,
            27.702104
          ],
          [
            36.701952,
            27.703412
          ],
          [
            36.714974,
            27.704921
          ],
          [
            36.727964,
            27.706629
          ],
          [
            36.74092,
            27.708536
          ],
          [
            36.753836,
            27.710642
          ],
          [
            36.766709,
            27.712946
          ],
          [
            36.779536,
            27.715448
          ],
          [
            36.792311,
            27.718146
          ],
          [
            36.805033,
            27.72104
          ],
          [
            36.817696,
            27.724128
          ],
          [
            36.830297,
            27.727411
          ],
          [
            36.842832,
            27.730887
          ],
          [
            36.855298,
            27.734555
          ],
          [
            36.86769,
            27.738413
          ],
          [
            36.880005,
            27.742462
          ],
          [
            36.89224,
            27.746699
          ],
          [
            36.90439,
            27.751123
          ],
          [
            36.916451,
            27.755733
          ],
          [
            36.928422,
            27.760527
          ],
          [
            36.940297,
            27.765505
          ],
          [
            36.952073,
            27.770664
          ],
          [
            36.963746,
            27.776004
          ],
          [
            36.975314,
            27.781522
          ],
          [
            36.986772,
            27.787216
          ],
          [
            36.998118,
            27.793086
          ],
          [
            37.009347,
            27.799129
          ],
          [
            37.020456,
            27.805344
          ],
          [
            37.031443,
            27.811728
          ],
          [
            37.042303,
            27.818281
          ],
          [
            37.053034,
            27.824999
          ],
          [
            37.063631,
            27.83188
          ],
          [
            37.074093,
            27.838924
          ],
          [
            37.084415,
            27.846127
          ],
          [
            37.094596,
            27.853487
          ],
          [
            37.10463,
            27.861003
          ],
          [
            37.114516,
            27.868671
          ],
          [
            37.124251,
            27.876491
          ],
          [
            37.133831,
            27.884458
          ],
          [
            37.143254,
            27.892572
          ],
          [
            37.152517,
            27.900829
          ],
          [
            37.161616,
            27.909227
          ],
          [
            37.17055,
            27.917763
          ],
          [
            37.179316,
            27.926436
          ],
          [
            37.18791,
            27.935242
          ],
          [
            37.19633,
            27.944178
          ],
          [
            37.204574,
            27.953242
          ],
          [
            37.212638,
            27.962432
          ],
          [
            37.220522,
            27.971744
          ],
          [
            37.228221,
            27.981175
          ],
          [
            37.235735,
            27.990724
          ],
          [
            37.24306,
            28.000386
          ],
          [
            37.250194,
            28.01016
          ],
          [
            37.257135,
            28.020041
          ],
          [
            37.263881,
            28.030028
          ],
          [
            37.270429,
            28.040117
          ],
          [
            37.276779,
            28.050304
          ],
          [
            37.282927,
            28.060588
          ],
          [
            37.288872,
            28.070965
          ],
          [
            37.294612,
            28.081431
          ],
          [
            37.300146,
            28.091984
          ],
          [
            37.30547,
            28.10262
          ],
          [
            37.310585,
            28.113336
          ],
          [
            37.315488,
            28.12413
          ],
          [
            37.320177,
            28.134997
          ],
          [
            37.324652,
            28.145934
          ],
          [
            37.32891,
            28.156938
          ],
          [
            37.332951,
            28.168006
          ],
          [
            37.336773,
            28.179135
          ],
          [
            37.340375,
            28.19032
          ],
          [
            37.343755,
            28.201559
          ],
          [
            37.346913,
            28.212849
          ],
          [
            37.349848,
            28.224185
          ],
          [
            37.352558,
            28.235564
          ],
          [
            37.355043,
            28.246984
          ],
          [
            37.357302,
            28.258439
          ],
          [
            37.359334,
            28.269928
          ],
          [
            37.361139,
            28.281446
          ],
          [
            37.362715,
            28.29299
          ],
          [
            37.364063,
            28.304557
          ],
          [
            37.365181,
            28.316142
          ],
          [
            37.36607,
            28.327743
          ],
          [
            37.366729,
            28.339356
          ],
          [
            37.367157,
            28.350977
          ],
          [
            37.367356,
            28.362603
          ],
          [
            37.367323,
            28.374231
          ],
          [
            37.36706,
            28.385856
          ],
          [
            37.366567,
            28.397475
          ],
          [
            37.365842,
            28.409084
          ],
          [
            37.364888,
            28.420681
          ],
          [
            37.363703,
            28.432262
          ],
          [
            37.362288,
            28.443822
          ],
          [
            37.360644,
            28.455359
          ],
          [
            37.358771,
            28.46687
          ],
          [
            37.356668,
            28.478349
          ],
          [
            37.354338,
            28.489795
          ],
          [
            37.351781,
            28.501202
          ],
          [
            37.348996,
            28.512569
          ],
          [
            37.345986,
            28.523892
          ],
          [
            37.342751,
            28.535166
          ],
          [
            37.339291,
            28.546389
          ],
          [
            37.335609,
            28.557558
          ],
          [
            37.331704,
            28.568668
          ],
          [
            37.327578,
            28.579716
          ],
          [
            37.323232,
            28.590699
          ],
          [
            37.318668,
            28.601614
          ],
          [
            37.313887,
            28.612457
          ],
          [
            37.308889,
            28.623225
          ],
          [
            37.303678,
            28.633915
          ],
          [
            37.298253,
            28.644523
          ],
          [
            37.292617,
            28.655046
          ],
          [
            37.286772,
            28.66548
          ],
          [
            37.280719,
            28.675824
          ],
          [
            37.27446,
            28.686073
          ],
          [
            37.267997,
            28.696224
          ],
          [
            37.261331,
            28.706275
          ],
          [
            37.254466,
            28.716221
          ],
          [
            37.247402,
            28.726061
          ],
          [
            37.240142,
            28.73579
          ],
          [
            37.232688,
            28.745407
          ],
          [
            37.225042,
            28.754908
          ],
          [
            37.217207,
            28.764289
          ],
          [
            37.209185,
            28.77355
          ],
          [
            37.200979,
            28.782685
          ],
          [
            37.19259,
            28.791693
          ],
          [
            37.184022,
            28.800571
          ],
          [
            37.175277,
            28.809316
          ],
          [
            37.166358,
            28.817925
          ],
          [
            37.157267,
            28.826396
          ],
          [
            37.148007,
            28.834726
          ],
          [
            37.138581,
            28.842912
          ],
          [
            37.128993,
            28.850953
          ],
          [
            37.119243,
            28.858845
          ],
          [
            37.109337,
            28.866586
          ],
          [
            37.099277,
            28.874174
          ],
          [
            37.089065,
            28.881606
          ],
          [
            37.078705,
            28.88888
          ],
          [
            37.068201,
            28.895994
          ],
          [
            37.057554,
            28.902945
          ],
          [
            37.04677,
            28.909732
          ],
          [
            37.03585,
            28.916352
          ],
          [
            37.024799,
            28.922804
          ],
          [
            37.013619,
            28.929085
          ],
          [
            37.002315,
            28.935193
          ],
          [
            36.990889,
            28.941127
          ],
          [
            36.979345,
            28.946884
          ],
          [
            36.967687,
            28.952463
          ],
          [
            36.955918,
            28.957862
          ],
          [
            36.944042,
            28.96308
          ],
          [
            36.932063,
            28.968114
          ],
          [
            36.919984,
            28.972964
          ],
          [
            36.907809,
            28.977628
          ],
          [
            36.895542,
            28.982103
          ],
          [
            36.883186,
            28.98639
          ],
          [
            36.870745,
            28.990486
          ],
          [
            36.858224,
            28.994391
          ],
          [
            36.845626,
            28.998103
          ],
          [
            36.832955,
            29.00162
          ],
          [
            36.820215,
            29.004943
          ],
          [
            36.80741,
            29.008069
          ],
          [
            36.794543,
            29.010998
          ],
          [
            36.781619,
            29.01373
          ],
          [
            36.768643,
            29.016262
          ],
          [
            36.755617,
            29.018594
          ],
          [
            36.742545,
            29.020727
          ],
          [
            36.729433,
            29.022658
          ],
          [
            36.716284,
            29.024387
          ],
          [
            36.703102,
            29.025915
          ],
          [
            36.689891,
            29.027239
          ],
          [
            36.676655,
            29.028361
          ],
          [
            36.663399,
            29.029279
          ],
          [
            36.650126,
            29.029993
          ],
          [
            36.636841,
            29.030503
          ],
          [
            36.623548,
            29.03081
          ],
          [
            36.61025,
            29.030912
          ],
          [
            36.596952,
            29.03081
          ]
        ]
      ]
    ]
  }
}