{
    "type": "Feature",
    "properties": {
      "id": "GMMN",
      "prefix": [
        "GMMN"
      ],
      "name": "Mohammed V Approach",
      "label_lat": 33.368851944444,
      "label_lon": -7.590545
    },
    "geometry": {
      "type": "MultiPolygon",
      "coordinates": [
        [
          [
            [
              33,
              -6.9333333333333
            ],
            [
              32.6547,
              -7.1591333333333
            ],
            [
              32.619619444444,
              -7.3663277777778
            ],
            [
              32.760347222222,
              -8.4128638888889
            ],
            [
              33.518927777778,
              -8.4747222222222
            ],
            [
              33.518931666667,
              -8.4763238888889
            ],
            [
              33.623208333333,
              -8.4664863888889
            ],
            [
              33.725039444444,
              -8.4372161111111
            ],
            [
              33.821904166667,
              -8.3892325
            ],
            [
              33.9113975,
              -8.3237166666667
            ],
            [
              33.991288888889,
              -8.2422802777778
            ],
            [
              34.059582222222,
              -8.1469275
            ],
            [
              34.114566111111,
              -8.0400058333333
            ],
            [
              34.154859444444,
              -7.9241477777778
            ],
            [
              34.179448888889,
              -7.8022066666667
            ],
            [
              34.187222222222,
              -7.7383333333333
            ],
            [
              34.330555555556,
              -7.3816666666667
            ],
            [
              34.600555555556,
              -7.015
            ],
            [
              34.497222222222,
              -6.3316666666667
            ],
            [
              34.196541666667,
              -6.2127722222222
            ],
            [
              34.1928725,
              -6.2110625
            ],
            [
              34.121625555556,
              -6.1904452777778
            ],
            [
              34.0486425,
              -6.1835161111111
            ],
            [
              33.975722222222,
              -6.1904452777778
            ],
            [
              33.904657777778,
              -6.2110625
            ],
            [
              33.837191666667,
              -6.2448602777778
            ],
            [
              33.774975277778,
              -6.2910069444444
            ],
            [
              33.719527222222,
              -6.3483663888889
            ],
            [
              33.710769444444,
              -6.3607666666667
            ],
            [
              33.5225,
              -6.5983333333333
            ]
          ]
        ]
      ]
    }
  }