{
  "type": "Feature",
  "properties": {
    "id": "VTCP",
    "prefix": [
      "VTCP"
    ],
    "name": "Phrae Approach"
  },
  "geometry": {
    "type": "MultiPolygon",
    "coordinates": [
      [
        [
          [
            99.853893,
            17.982627
          ],
          [
            99.840556,
            18.013315
          ],
          [
            99.857096,
            18.03156
          ],
          [
            99.893048,
            18.087201
          ],
          [
            99.91938,
            18.14751
          ],
          [
            99.935443,
            18.211007
          ],
          [
            99.940841,
            18.276131
          ],
          [
            99.935443,
            18.341279
          ],
          [
            99.926619,
            18.376376
          ],
          [
            99.960177,
            18.403486
          ],
          [
            100.007074,
            18.430842
          ],
          [
            100.038361,
            18.442944
          ],
          [
            100.01205,
            18.61485
          ],
          [
            100.083956,
            18.627599
          ],
          [
            100.166208,
            18.633769
          ],
          [
            100.18,
            18.634556
          ],
          [
            100.203333,
            18.467944
          ],
          [
            100.221042,
            18.463106
          ],
          [
            100.274526,
            18.45088
          ],
          [
            100.327072,
            18.431383
          ],
          [
            100.37224,
            18.403486
          ],
          [
            100.414064,
            18.36949
          ],
          [
            100.449786,
            18.329694
          ],
          [
            100.460747,
            18.315125
          ],
          [
            100.478524,
            18.285081
          ],
          [
            100.499572,
            18.236754
          ],
          [
            100.512412,
            18.185906
          ],
          [
            100.516728,
            18.133789
          ],
          [
            100.512412,
            18.081687
          ],
          [
            100.499572,
            18.030883
          ],
          [
            100.478524,
            17.982627
          ],
          [
            100.463333,
            17.951333
          ],
          [
            100.579972,
            17.826333
          ],
          [
            100.537996,
            17.780437
          ],
          [
            100.475259,
            17.729626
          ],
          [
            100.404913,
            17.688757
          ],
          [
            100.328687,
            17.658831
          ],
          [
            100.248461,
            17.640577
          ],
          [
            100.166208,
            17.634442
          ],
          [
            100.121694,
            17.634694
          ],
          [
            100.111374,
            17.80509
          ],
          [
            100.057891,
            17.81727
          ],
          [
            100.007074,
            17.837239
          ],
          [
            99.960177,
            17.864506
          ],
          [
            99.918353,
            17.898404
          ],
          [
            99.882631,
            17.938103
          ],
          [
            99.853893,
            17.982627
          ]
        ]
      ]
    ]
  }
}