{
  "type": "Feature",
  "properties": {
    "id": "SBWB",
    "prefix": [
      "SBWB"
    ],
    "name": "Belem Control"
  },
  "geometry": {
    "type": "MultiPolygon",
    "coordinates": [
      [
        [
          [
            -48.478667,
            -0.714379
          ],
          [
            -48.450798,
            -0.714966
          ],
          [
            -48.422978,
            -0.716728
          ],
          [
            -48.395256,
            -0.71966
          ],
          [
            -48.36768,
            -0.723759
          ],
          [
            -48.340299,
            -0.729015
          ],
          [
            -48.31316,
            -0.735422
          ],
          [
            -48.286312,
            -0.742966
          ],
          [
            -48.259801,
            -0.751636
          ],
          [
            -48.233673,
            -0.761415
          ],
          [
            -48.207976,
            -0.772286
          ],
          [
            -48.182752,
            -0.784231
          ],
          [
            -48.158048,
            -0.797229
          ],
          [
            -48.133906,
            -0.811257
          ],
          [
            -48.110368,
            -0.826289
          ],
          [
            -48.087476,
            -0.842301
          ],
          [
            -48.06527,
            -0.859263
          ],
          [
            -48.043789,
            -0.877146
          ],
          [
            -48.02307,
            -0.895919
          ],
          [
            -48.00315,
            -0.915548
          ],
          [
            -47.984064,
            -0.936
          ],
          [
            -47.965845,
            -0.957238
          ],
          [
            -47.948526,
            -0.979226
          ],
          [
            -47.932136,
            -1.001924
          ],
          [
            -47.916704,
            -1.025293
          ],
          [
            -47.902258,
            -1.049292
          ],
          [
            -47.888823,
            -1.073878
          ],
          [
            -47.876422,
            -1.099009
          ],
          [
            -47.865077,
            -1.124641
          ],
          [
            -47.854809,
            -1.150728
          ],
          [
            -47.845634,
            -1.177226
          ],
          [
            -47.837569,
            -1.204086
          ],
          [
            -47.830629,
            -1.231263
          ],
          [
            -47.824826,
            -1.258709
          ],
          [
            -47.820169,
            -1.286375
          ],
          [
            -47.816667,
            -1.314213
          ],
          [
            -47.814327,
            -1.342174
          ],
          [
            -47.813152,
            -1.370209
          ],
          [
            -47.813144,
            -1.398269
          ],
          [
            -47.814303,
            -1.426305
          ],
          [
            -47.816629,
            -1.454268
          ],
          [
            -47.820115,
            -1.482108
          ],
          [
            -47.824757,
            -1.509776
          ],
          [
            -47.830546,
            -1.537225
          ],
          [
            -47.837473,
            -1.564406
          ],
          [
            -47.845524,
            -1.591271
          ],
          [
            -47.854686,
            -1.617773
          ],
          [
            -47.864944,
            -1.643865
          ],
          [
            -47.876278,
            -1.669503
          ],
          [
            -47.88867,
            -1.69464
          ],
          [
            -47.902096,
            -1.719233
          ],
          [
            -47.916535,
            -1.743239
          ],
          [
            -47.931961,
            -1.766615
          ],
          [
            -47.948346,
            -1.78932
          ],
          [
            -47.965662,
            -1.811315
          ],
          [
            -47.983878,
            -1.832561
          ],
          [
            -48.002963,
            -1.85302
          ],
          [
            -48.022883,
            -1.872658
          ],
          [
            -48.043604,
            -1.891438
          ],
          [
            -48.065088,
            -1.909329
          ],
          [
            -48.087298,
            -1.926299
          ],
          [
            -48.110196,
            -1.942317
          ],
          [
            -48.13374,
            -1.957357
          ],
          [
            -48.15789,
            -1.971391
          ],
          [
            -48.182603,
            -1.984395
          ],
          [
            -48.207837,
            -1.996346
          ],
          [
            -48.233545,
            -2.007223
          ],
          [
            -48.259685,
            -2.017007
          ],
          [
            -48.286209,
            -2.025681
          ],
          [
            -48.31307,
            -2.03323
          ],
          [
            -48.340223,
            -2.039639
          ],
          [
            -48.367619,
            -2.044899
          ],
          [
            -48.39521,
            -2.049
          ],
          [
            -48.422947,
            -2.051934
          ],
          [
            -48.450782,
            -2.053696
          ],
          [
            -48.478667,
            -2.054284
          ],
          [
            -48.506551,
            -2.053696
          ],
          [
            -48.534386,
            -2.051934
          ],
          [
            -48.562124,
            -2.049
          ],
          [
            -48.589714,
            -2.044899
          ],
          [
            -48.61711,
            -2.039639
          ],
          [
            -48.644263,
            -2.03323
          ],
          [
            -48.671125,
            -2.025681
          ],
          [
            -48.697649,
            -2.017007
          ],
          [
            -48.723788,
            -2.007223
          ],
          [
            -48.749497,
            -1.996346
          ],
          [
            -48.77473,
            -1.984395
          ],
          [
            -48.799443,
            -1.971391
          ],
          [
            -48.823593,
            -1.957357
          ],
          [
            -48.847138,
            -1.942317
          ],
          [
            -48.870035,
            -1.926299
          ],
          [
            -48.892245,
            -1.909329
          ],
          [
            -48.91373,
            -1.891438
          ],
          [
            -48.93445,
            -1.872658
          ],
          [
            -48.95437,
            -1.85302
          ],
          [
            -48.973455,
            -1.832561
          ],
          [
            -48.991672,
            -1.811315
          ],
          [
            -49.008987,
            -1.78932
          ],
          [
            -49.025373,
            -1.766615
          ],
          [
            -49.040798,
            -1.743239
          ],
          [
            -49.055237,
            -1.719233
          ],
          [
            -49.068664,
            -1.69464
          ],
          [
            -49.081055,
            -1.669503
          ],
          [
            -49.09239,
            -1.643865
          ],
          [
            -49.102647,
            -1.617773
          ],
          [
            -49.111809,
            -1.591271
          ],
          [
            -49.119861,
            -1.564406
          ],
          [
            -49.126787,
            -1.537225
          ],
          [
            -49.132576,
            -1.509776
          ],
          [
            -49.137218,
            -1.482108
          ],
          [
            -49.140705,
            -1.454268
          ],
          [
            -49.14303,
            -1.426305
          ],
          [
            -49.14419,
            -1.398269
          ],
          [
            -49.144182,
            -1.370209
          ],
          [
            -49.143006,
            -1.342174
          ],
          [
            -49.140666,
            -1.314213
          ],
          [
            -49.137164,
            -1.286375
          ],
          [
            -49.132507,
            -1.258709
          ],
          [
            -49.126704,
            -1.231263
          ],
          [
            -49.119764,
            -1.204086
          ],
          [
            -49.111699,
            -1.177226
          ],
          [
            -49.102525,
            -1.150728
          ],
          [
            -49.092256,
            -1.124641
          ],
          [
            -49.080911,
            -1.099009
          ],
          [
            -49.06851,
            -1.073878
          ],
          [
            -49.055075,
            -1.049292
          ],
          [
            -49.040629,
            -1.025293
          ],
          [
            -49.025197,
            -1.001924
          ],
          [
            -49.008808,
            -0.979226
          ],
          [
            -48.991488,
            -0.957238
          ],
          [
            -48.973269,
            -0.936
          ],
          [
            -48.954183,
            -0.915548
          ],
          [
            -48.934263,
            -0.895919
          ],
          [
            -48.913545,
            -0.877146
          ],
          [
            -48.892064,
            -0.859263
          ],
          [
            -48.869857,
            -0.842301
          ],
          [
            -48.846965,
            -0.826289
          ],
          [
            -48.823428,
            -0.811257
          ],
          [
            -48.799285,
            -0.797229
          ],
          [
            -48.774581,
            -0.784231
          ],
          [
            -48.749358,
            -0.772286
          ],
          [
            -48.72366,
            -0.761415
          ],
          [
            -48.697532,
            -0.751636
          ],
          [
            -48.671021,
            -0.742966
          ],
          [
            -48.644173,
            -0.735422
          ],
          [
            -48.617034,
            -0.729015
          ],
          [
            -48.589653,
            -0.723759
          ],
          [
            -48.562077,
            -0.71966
          ],
          [
            -48.534355,
            -0.716728
          ],
          [
            -48.506535,
            -0.714966
          ],
          [
            -48.478667,
            -0.714379
          ]
        ]
      ]
    ]
  }
}