{
    "type": "Feature",
    "properties": {
        "id": "WAPP",
        "prefix": [
            "WAPP"
        ],
        "name": "Ambon Approach"
    },
    "geometry": {
        "type": "MultiPolygon",
        "coordinates": [
            [
                [
                    [
                        128.186061,
                        -1.9493753858385
                    ],
                    [
                        128.44720105225,
                        -1.9698492840523
                    ],
                    [
                        128.701900604,
                        -2.030768341769
                    ],
                    [
                        128.94388000301,
                        -2.130637026443
                    ],
                    [
                        129.16717683871,
                        -2.2670037075302
                    ],
                    [
                        129.3662936438,
                        -2.4365208807184
                    ],
                    [
                        129.53633307444,
                        -2.6350272225264
                    ],
                    [
                        129.67311728216,
                        -2.8576493534898
                    ],
                    [
                        129.77328880466,
                        -3.0989207545105
                    ],
                    [
                        129.8343909238,
                        -3.3529149406642
                    ],
                    [
                        129.85492601599,
                        -3.6133897405537
                    ],
                    [
                        129.8343909238,
                        -3.8739393411546
                    ],
                    [
                        129.77328880466,
                        -4.1281506206499
                    ],
                    [
                        129.67311728216,
                        -4.3697601916549
                    ],
                    [
                        129.53633307444,
                        -4.59280850962
                    ],
                    [
                        129.3662936438,
                        -4.791787371948
                    ],
                    [
                        129.16717683871,
                        -4.9617771588344
                    ],
                    [
                        128.94388000301,
                        -5.0985702708669
                    ],
                    [
                        128.701900604,
                        -5.198777427056
                    ],
                    [
                        128.44720105225,
                        -5.259913822058
                    ],
                    [
                        128.186061,
                        -5.2804626141615
                    ],
                    [
                        127.92492094775,
                        -5.259913822058
                    ],
                    [
                        127.670221396,
                        -5.198777427056
                    ],
                    [
                        127.42824199699,
                        -5.0985702708669
                    ],
                    [
                        127.20494516129,
                        -4.9617771588344
                    ],
                    [
                        127.0058283562,
                        -4.791787371948
                    ],
                    [
                        126.83578892556,
                        -4.59280850962
                    ],
                    [
                        126.69900471784,
                        -4.3697601916549
                    ],
                    [
                        126.59883319534,
                        -4.1281506206499
                    ],
                    [
                        126.5377310762,
                        -3.8739393411546
                    ],
                    [
                        126.51719598401,
                        -3.6133897405537
                    ],
                    [
                        126.5377310762,
                        -3.3529149406642
                    ],
                    [
                        126.59883319534,
                        -3.0989207545105
                    ],
                    [
                        126.69900471784,
                        -2.8576493534898
                    ],
                    [
                        126.83578892556,
                        -2.6350272225264
                    ],
                    [
                        127.0058283562,
                        -2.4365208807184
                    ],
                    [
                        127.20494516129,
                        -2.2670037075302
                    ],
                    [
                        127.42824199699,
                        -2.130637026443
                    ],
                    [
                        127.670221396,
                        -2.030768341769
                    ],
                    [
                        127.92492094775,
                        -1.9698492840523
                    ],
                    [
                        128.186061,
                        -1.9493753858385
                    ]
                ]
            ]
        ]
    }
}