{
  "type": "Feature",
  "properties": {
    "id": "MMMD",
    "prefix": [
      "MMMD"
    ],
    "name": "Merida TMA"
  },
  "geometry": {
    "type": "MultiPolygon",
    "coordinates": [
      [
        [
          [
            -90.603614,
            21.702806
          ],
          [
            -90.446739,
            21.847033
          ],
          [
            -90.446739,
            21.847033
          ],
          [
            -90.126269,
            21.649906
          ],
          [
            -90.090858,
            21.669128
          ],
          [
            -90.055014,
            21.687497
          ],
          [
            -90.023642,
            21.700394
          ],
          [
            -89.979844,
            21.7178
          ],
          [
            -89.937408,
            21.732631
          ],
          [
            -89.894247,
            21.74425
          ],
          [
            -89.849422,
            21.755803
          ],
          [
            -89.787281,
            21.765803
          ],
          [
            -89.729258,
            21.771933
          ],
          [
            -89.683375,
            21.775469
          ],
          [
            -89.628803,
            21.775792
          ],
          [
            -89.578969,
            21.772561
          ],
          [
            -89.515767,
            21.765147
          ],
          [
            -89.453575,
            21.753217
          ],
          [
            -89.384331,
            21.736111
          ],
          [
            -89.335658,
            21.719831
          ],
          [
            -89.276436,
            21.696322
          ],
          [
            -89.209706,
            21.663683
          ],
          [
            -89.149311,
            21.628
          ],
          [
            -89.095808,
            21.588728
          ],
          [
            -89.057667,
            21.558992
          ],
          [
            -89.031061,
            21.536142
          ],
          [
            -88.995089,
            21.499236
          ],
          [
            -88.966922,
            21.468214
          ],
          [
            -88.936381,
            21.431947
          ],
          [
            -88.911583,
            21.396331
          ],
          [
            -88.890681,
            21.365672
          ],
          [
            -88.867286,
            21.325803
          ],
          [
            -88.84575,
            21.283778
          ],
          [
            -88.828542,
            21.247633
          ],
          [
            -88.812344,
            21.204728
          ],
          [
            -88.797797,
            21.160611
          ],
          [
            -88.782697,
            21.099681
          ],
          [
            -88.775706,
            21.057622
          ],
          [
            -88.769264,
            21.005111
          ],
          [
            -88.767258,
            20.938794
          ],
          [
            -88.768075,
            20.884256
          ],
          [
            -88.777708,
            20.808039
          ],
          [
            -88.787661,
            20.757178
          ],
          [
            -88.813703,
            20.672744
          ],
          [
            -88.835181,
            20.622231
          ],
          [
            -88.859556,
            20.569614
          ],
          [
            -88.882031,
            20.528581
          ],
          [
            -88.909192,
            20.488592
          ],
          [
            -88.943639,
            20.441606
          ],
          [
            -88.9754,
            20.402286
          ],
          [
            -89.011639,
            20.365467
          ],
          [
            -89.050428,
            20.327756
          ],
          [
            -89.099606,
            20.289169
          ],
          [
            -89.135744,
            20.264047
          ],
          [
            -89.174503,
            20.238258
          ],
          [
            -89.214936,
            20.215836
          ],
          [
            -89.258731,
            20.194306
          ],
          [
            -89.304939,
            20.174108
          ],
          [
            -89.352606,
            20.155692
          ],
          [
            -89.415306,
            20.135642
          ],
          [
            -89.473433,
            20.12265
          ],
          [
            -89.540225,
            20.112792
          ],
          [
            -89.609472,
            20.106953
          ],
          [
            -89.677039,
            20.104772
          ],
          [
            -89.753431,
            20.110161
          ],
          [
            -89.812586,
            20.117781
          ],
          [
            -89.866706,
            20.129042
          ],
          [
            -89.943853,
            20.149878
          ],
          [
            -90.018386,
            20.176808
          ],
          [
            -90.0675,
            20.198811
          ],
          [
            -90.114278,
            20.224525
          ],
          [
            -90.155714,
            20.249228
          ],
          [
            -90.201069,
            20.280239
          ],
          [
            -90.239411,
            20.309403
          ],
          [
            -90.272242,
            20.338164
          ],
          [
            -90.302211,
            20.365136
          ],
          [
            -90.327386,
            20.391228
          ],
          [
            -90.3492,
            20.414181
          ],
          [
            -90.361828,
            20.430397
          ],
          [
            -90.673022,
            20.256981
          ],
          [
            -90.780394,
            20.427964
          ],
          [
            -90.473381,
            20.601839
          ],
          [
            -90.481786,
            20.622703
          ],
          [
            -90.829086,
            20.53255
          ],
          [
            -90.86955,
            20.669308
          ],
          [
            -90.890686,
            20.751603
          ],
          [
            -90.898189,
            20.815208
          ],
          [
            -90.904833,
            20.870642
          ],
          [
            -90.906172,
            20.912753
          ],
          [
            -90.905744,
            20.981564
          ],
          [
            -90.903961,
            21.016667
          ],
          [
            -90.893817,
            21.067356
          ],
          [
            -90.867353,
            21.217269
          ],
          [
            -90.472178,
            21.272278
          ],
          [
            -90.467711,
            21.283053
          ],
          [
            -90.829019,
            21.335881
          ],
          [
            -90.737356,
            21.526536
          ],
          [
            -90.346506,
            21.468486
          ],
          [
            -90.302425,
            21.515892
          ],
          [
            -90.603614,
            21.702806
          ]
        ]
      ]
    ]
  }
}