{
  "type": "Feature",
  "properties": {
    "id": "OGG",
    "prefix": [
      "OGG"
    ],
    "name": "HCF Approach"
  },
  "geometry": {
    "type": "MultiPolygon",
    "coordinates": [
      [
        [
          [
            -156.85335,
            20.61378
          ],
          [
            -156.36316,
            20.4711
          ],
          [
            -156.34924,
            20.58702
          ],
          [
            -156.13302,
            20.72832
          ],
          [
            -156.02503,
            20.67269
          ],
          [
            -155.78603,
            20.63461
          ],
          [
            -155.76937,
            20.91849
          ],
          [
            -155.9753,
            20.95284
          ],
          [
            -155.99631,
            21.04414
          ],
          [
            -156.04955,
            21.13364
          ],
          [
            -156.15018,
            21.23464
          ],
          [
            -156.30486,
            21.30523
          ],
          [
            -156.42404,
            21.31615
          ],
          [
            -156.69329,
            21.22669
          ],
          [
            -156.82939,
            21.06844
          ],
          [
            -156.86448,
            20.95604
          ],
          [
            -156.78789,
            20.74798
          ],
          [
            -156.85335,
            20.61378
          ]
        ]
      ]
    ]
  }
}