{
  "type": "Feature",
  "properties": {
    "id": "YBNA",
    "name": "Ballina Approach",
    "prefix": [
      "BA"
    ]
  },
  "geometry": {
    "type": "MultiPolygon",
    "coordinates": [
      [
        [
          [
            153.054444,
            -28.474167
          ],
          [
            152.956944,
            -28.850556
          ],
          [
            152.941667,
            -28.908611
          ],
          [
            152.898611,
            -29.303056
          ],
          [
            153.013475,
            -29.34263
          ],
          [
            153.254762,
            -29.399673
          ],
          [
            153.503889,
            -29.418889
          ],
          [
            153.753016,
            -29.399673
          ],
          [
            153.808611,
            -29.393056
          ],
          [
            153.847778,
            -29.211944
          ],
          [
            153.891389,
            -29.008333
          ],
          [
            153.903056,
            -28.952778
          ],
          [
            153.938333,
            -28.788056
          ],
          [
            153.937018,
            -28.775489
          ],
          [
            153.919669,
            -28.719412
          ],
          [
            153.891503,
            -28.666823
          ],
          [
            153.853388,
            -28.619314
          ],
          [
            153.8175,
            -28.586667
          ],
          [
            153.788634,
            -28.601607
          ],
          [
            153.698734,
            -28.638597
          ],
          [
            153.602836,
            -28.661257
          ],
          [
            153.503889,
            -28.668889
          ],
          [
            153.404942,
            -28.661257
          ],
          [
            153.309043,
            -28.638597
          ],
          [
            153.219143,
            -28.601607
          ],
          [
            153.138001,
            -28.551425
          ],
          [
            153.068095,
            -28.489593
          ],
          [
            153.054444,
            -28.474167
          ]
        ]
      ]
    ]
  }
}