{
  "type": "Feature",
  "properties": {
    "id": "MFR",
    "prefix": [
      "MFR"
    ],
    "name": "Medford Approach"
  },
  "geometry": {
    "type": "MultiPolygon",
    "coordinates": [
      [
        [
          [
            -122.875,
            42.933333
          ],
          [
            -122.416667,
            42.7
          ],
          [
            -122.416667,
            42.433333
          ],
          [
            -122.416667,
            42.383333
          ],
          [
            -122.416667,
            42.0
          ],
          [
            -123.233333,
            42.0
          ],
          [
            -123.483333,
            42.316667
          ],
          [
            -123.452778,
            42.418056
          ],
          [
            -123.404167,
            42.652778
          ],
          [
            -123.383333,
            42.741667
          ],
          [
            -123.083333,
            42.933333
          ],
          [
            -122.875,
            42.933333
          ]
        ]
      ]
    ]
  }
}