{
  "type": "Feature",
  "properties": {
    "id": "PCT",
    "prefix": [
      "PCT"
    ],
    "name": "Potomac Approach"
  },
  "geometry": {
    "type": "MultiPolygon",
    "coordinates": [
      [
        [
          [
            -75.59,
            38.705833
          ],
          [
            -75.55,
            38.616667
          ],
          [
            -75.1,
            38.5
          ],
          [
            -74.989167,
            38.5
          ],
          [
            -74.989444,
            38.418889
          ],
          [
            -75.05,
            38.266667
          ],
          [
            -75.333333,
            37.820833
          ],
          [
            -75.417222,
            37.82
          ],
          [
            -75.5,
            37.713333
          ],
          [
            -75.5,
            37.56667
          ],
          [
            -76.025,
            37.66667
          ],
          [
            -76.16667,
            37.66667
          ],
          [
            -76.1925,
            37.75
          ],
          [
            -76.39167,
            37.75
          ],
          [
            -76.46667,
            37.6
          ],
          [
            -76.45694,
            37.51222
          ],
          [
            -76.57306,
            37.50361
          ],
          [
            -76.77417,
            37.48861
          ],
          [
            -76.85194,
            37.46028
          ],
          [
            -76.88056,
            37.40278
          ],
          [
            -76.90694,
            37.34722
          ],
          [
            -77.0,
            37.23333
          ],
          [
            -77.21667,
            36.90556
          ],
          [
            -77.3038867,
            36.9024925
          ],
          [
            -77.5333306,
            36.8833256
          ],
          [
            -77.8448656,
            37.0183356
          ],
          [
            -77.8435736,
            37.0455464
          ],
          [
            -77.8509969,
            37.0656369
          ],
          [
            -77.8621756,
            37.0739792
          ],
          [
            -77.8645758,
            37.0939225
          ],
          [
            -77.8647264,
            37.1468453
          ],
          [
            -77.9993081,
            37.24659
          ],
          [
            -78.1666333,
            37.2606075
          ],
          [
            -78.171944,
            37.534444
          ],
          [
            -78.4791833,
            37.6021725
          ],
          [
            -78.55665,
            37.61995
          ],
          [
            -78.6056169,
            37.6294153
          ],
          [
            -79.2706725,
            37.7813414
          ],
          [
            -79.2952625,
            38.0519283
          ],
          [
            -79.3249969,
            38.3499922
          ],
          [
            -78.7822522,
            38.4563217
          ],
          [
            -78.3233253,
            38.5468594
          ],
          [
            -78.3749681,
            38.5667108
          ],
          [
            -78.3749814,
            38.8143603
          ],
          [
            -78.375,
            39.091944
          ],
          [
            -78.3750614,
            39.3481814
          ],
          [
            -78.7027778,
            39.3347222
          ],
          [
            -78.5222206,
            39.5916603
          ],
          [
            -78.485,
            39.6466669
          ],
          [
            -78.45111312972087,
            39.69587214606624
          ],
          [
            -77.933333,
            39.85
          ],
          [
            -77.840278,
            39.855556
          ],
          [
            -77.3580108,
            39.8750631
          ],
          [
            -77.1591872,
            39.8806236
          ],
          [
            -76.9755331,
            39.8836203
          ],
          [
            -76.9712160223096,
            39.8836292103689
          ],
          [
            -76.9172017,
            39.8838806
          ],
          [
            -76.8695537980856,
            39.8840400065558
          ],
          [
            -76.7763858,
            39.8843517
          ],
          [
            -76.6918311,
            39.8845392
          ],
          [
            -76.5333453,
            39.8847461
          ],
          [
            -76.4019758,
            39.8589281
          ],
          [
            -76.211389,
            39.820278
          ],
          [
            -76.139722,
            39.725278
          ],
          [
            -76.040278,
            39.593611
          ],
          [
            -76.013333,
            39.557778
          ],
          [
            -75.87,
            39.335
          ],
          [
            -75.836111,
            39.266667
          ],
          [
            -75.875833,
            38.969444
          ],
          [
            -75.8325,
            38.863056
          ],
          [
            -75.666667,
            38.7
          ],
          [
            -75.59,
            38.705833
          ]
        ]
      ]
    ]
  }
}